MedCode/__init__.py
MedCode-1.3.0.dist-info/LICENSE
MedCode-1.3.0.dist-info/METADATA
MedCode-1.3.0.dist-info/WHEEL
MedCode-1.3.0.dist-info/entry_points.txt
MedCode-1.3.0.dist-info/top_level.txt
MedCode-1.3.0.dist-info/RECORD
