Metadata-Version: 2.1
Name: MedCode
Version: 1.3.0
Summary: A package for medical code mapping
Home-page: https://github.com/ycq091044/MedCode
Author: Chaoqi Yang
Author-email: chaoqiy2@illinois.edu
License: UNKNOWN
Platform: UNKNOWN
Classifier: Programming Language :: Python :: 3
Classifier: License :: OSI Approved :: MIT License
Classifier: Operating System :: OS Independent
License-File: LICENSE
Requires-Dist: networkx
Requires-Dist: pandas
